setup.py
django_variant.egg-info/PKG-INFO
django_variant.egg-info/SOURCES.txt
django_variant.egg-info/dependency_links.txt
django_variant.egg-info/requires.txt
django_variant.egg-info/top_level.txt
variant/__init__.py
variant/admin.py
variant/jinja.py
variant/middleware.py
variant/mixins.py
variant/models.py
variant/utils.py
variant/views.py
variant/migrations/0001_initial.py
variant/migrations/__init__.py