Metadata-Version: 1.1
Name: django-variant
Version: 0.1.1
Summary: Django variant testing framework
Home-page: https://github.com/jsatt/django-variant
Author: Jeremy Sattefield
Author-email: jsatt@jsatt.com
License: UNKNOWN
Platform: UNKNOWN
Classifier: Development Status :: 4 - Beta
Classifier: Environment :: Web Environment
Classifier: Framework :: Django
Classifier: Intended Audience :: Developers
Classifier: License :: OSI Approved :: GNU General Public License v3 (GPLv3)
Classifier: Natural Language :: English
Classifier: Operating System :: OS Independent
Classifier: Programming Language :: Python
Classifier: Topic :: Internet :: WWW/HTTP :: Site Management
